[
  {
    "Symbol": "ASNS",
    "Score": "100.74",
    "Buy Price": "0.50",
    "Target": "0.54",
    "Stop": "0.49",
    "AI Thesis": "Stock Data Currently Unavailable. Please check back momentarily.",
    "News": "No recent news found."
  },
  {
    "Symbol": "AG",
    "Score": "29.80",
    "Buy Price": "28.80",
    "Target": "30.81",
    "Stop": "27.79",
    "AI Thesis": "Stock Data Currently Unavailable. Please check back momentarily.",
    "News": "No recent news found."
  },
  {
    "Symbol": "AEM",
    "Score": "29.59",
    "Buy Price": "237.22",
    "Target": "253.82",
    "Stop": "228.91",
    "AI Thesis": "Stock Data Currently Unavailable. Please check back momentarily.",
    "News": "No recent news found."
  },
  {
    "Symbol": "ALGN",
    "Score": "29.40",
    "Buy Price": "184.09",
    "Target": "196.98",
    "Stop": "177.65",
    "AI Thesis": "Stock Data Currently Unavailable. Please check back momentarily.",
    "News": "No recent news found."
  },
  {
    "Symbol": "MOBX",
    "Score": "22.62",
    "Buy Price": "1.01",
    "Target": "1.08",
    "Stop": "0.97",
    "AI Thesis": "Stock Data Currently Unavailable. Please check back momentarily.",
    "News": "No recent news found."
  }
]